fintoolsom/__init__.py
fintoolsom/dates/__init__.py
fintoolsom/dates/datetools.py
fintoolsom/fixedIncome/Bonds.py
fintoolsom/fixedIncome/CLBonds.py
fintoolsom/fixedIncome/Deposits.py
fintoolsom/fixedIncome/__init__.py
fintoolsom/rates/Rates.py
fintoolsom/rates/ZeroCouponCurve.py
fintoolsom/rates/__init__.py
fintoolsom-0.1.15.dist-info/LICENSE
fintoolsom-0.1.15.dist-info/METADATA
fintoolsom-0.1.15.dist-info/WHEEL
fintoolsom-0.1.15.dist-info/top_level.txt
fintoolsom-0.1.15.dist-info/RECORD
