Metadata-Version: 2.1
Name: fintoolsom
Version: 0.1.15
Summary: Personal library for finantial calculations
Home-page: https://github.com/oliverm91/fintoolsom
Author: Oliver Mohr B.
Author-email: oliver.mohr.b@gmail.com
License: UNKNOWN
Keywords: fixed income,dates,rates,curves
Platform: UNKNOWN
Classifier: Development Status :: 3 - Alpha
Classifier: License :: OSI Approved :: GNU General Public License v3 (GPLv3)
Classifier: Programming Language :: Python
Classifier: Programming Language :: Python :: 3.8
Classifier: Programming Language :: Python :: 3.9
Classifier: Programming Language :: Python :: 3.10
Classifier: Programming Language :: Python :: 3.11
Classifier: Intended Audience :: Financial and Insurance Industry
Classifier: Intended Audience :: Developers
Classifier: Topic :: Office/Business :: Financial
Classifier: Natural Language :: English
Requires-Python: >=3.8
Requires-Dist: numpy
Requires-Dist: mathsom
